{
"date":"2018-01-02 09:47:01",
"roominfo":{"gamestate":1,"rulename":"1圈4局","ruleid":1,"serviceid":"bc882162ef5e11e7b51df7c5f889c43d","playTypeNum":"0,1,2,3,4,5,6,7,8,9,10,11","roomcircle":1,"mastername":"锋","roomid":183047,"playernum":3,"master":1007990},
"player":[{"uid":1007990,"nickname":"锋","head":"http://192.168.1.115/head/4.jpg","ip":"192.168.1.178","ipold":"192.168.1.178","lat":36.104886,"lon":120.357165,"chairid":0,"state":1,"score":0,"playstate":0,"sex":2},{"uid":1007991,"nickname":"小小","head":"http://192.168.1.115/head/4.jpg","ip":"192.168.1.138","ipold":"192.168.1.138","lat":39.90403,"lon":116.407525,"chairid":1,"state":1,"score":0,"playstate":0,"sex":1},{"uid":1007989,"nickname":"乐乐","head":"http://192.168.1.115/head/4.jpg","ip":"192.168.1.162","ipold":"192.168.1.162","chairid":2,"state":1,"score":0,"playstate":0,"sex":1}],
"roundinfo":{"dianshu1":3,"dianshu2":1,"zhuangjiachairid":0,"startchairid":1,"startpos":4,"frontremove":39,"tailremove":0,"leftcount":73,"curchairid":-1,"curoutcard":-1,"lefttime":0,"curaction":1,"curround":1,"curcircle":1,"difen":1,"lianzhuang":0,"huangzhuang":0,"des":"第1圈(1/4) 第1局"},
"carddata":[{"norcard":[79,110,16,80,81,65,28,96,24,84,4,73,71],"out":[],"weavecard":[],"ops":[],"lastout":-1},{"norcard":[27,99,6,0,12,10,44,49,67,21,97,55,47],"out":[],"weavecard":[],"ops":[],"lastout":-1},{"norcard":[102,100,48,5,54,36,105,63,62,107,91,40,30],"out":[],"weavecard":[],"ops":[],"lastout":-1}],
"actions":[
{"op":1,"leftcount":58,"frontremove":40,"cardid":58,"tailremove":0,"progress":3,"chairid":0,"lefttime":15,"opts":{"0":[],"1":[],"2":[]}},
{"op":2,"cardid":110,"progress":4,"chairid":0,"opts":{"0":[],"1":[],"2":[]}},
{"op":1,"leftcount":57,"frontremove":41,"cardid":33,"tailremove":0,"progress":5,"chairid":1,"lefttime":15,"opts":{"0":[],"1":[],"2":[]}},
{"op":2,"cardid":33,"progress":6,"chairid":1,"opts":{"0":[],"1":[],"2":[]}},
{"op":1,"leftcount":56,"frontremove":42,"cardid":61,"tailremove":0,"progress":7,"chairid":2,"lefttime":15,"opts":{"0":[],"1":[],"2":[]}},
{"op":2,"cardid":91,"progress":8,"chairid":2,"opts":{"0":[{"op":5,"item":[{"id":0,"info":[81,84,91],"rm":[81,84],"type":0,"lmtid":[16,80,81,65,28,96,24,84,4,73,71,58]}]}],"1":[],"2":[]}},
{"op":4,"select":{"0":5},"progress":8},
{"op":3,"progress":9,"chairid":0,"rm":[81,84],"card":{"type":0,"card":[-1,81,84,91],"chairid":2,"centercard":91,"flag":true},"lefttime":15,"opts":{"0":[],"1":[],"2":[]}},
{"op":2,"cardid":96,"progress":10,"chairid":0,"opts":{"0":[],"1":[{"op":3,"item":[{"id":0,"info":[99,97,96],"rm":[99,97],"type":0}]}],"2":[]}},
{"op":4,"select":{"1":3},"progress":10},
{"op":3,"progress":11,"chairid":1,"rm":[99,97],"card":{"type":1,"card":[-1,96,97,99],"chairid":0,"centercard":96,"flag":true},"lefttime":15,"opts":{"0":[],"1":[],"2":[]}},
{"op":2,"cardid":44,"progress":12,"chairid":1,"opts":{"0":[],"1":[],"2":[{"op":5,"item":[{"id":0,"info":[36,40,44],"rm":[36,40],"type":0,"lmtid":[102,100,48,5,54,36,105,63,62,107,40,30,61]},{"id":1,"info":[40,44,48],"rm":[40,48],"type":0,"lmtid":[102,100,48,5,54,36,105,63,62,107,40,30,61]},{"id":2,"info":[44,48,54],"rm":[48,54],"type":0,"lmtid":[102,100,48,5,54,36,105,63,62,107,40,30,61]}]}]}},
{"op":4,"select":{"2":5},"progress":12},
{"op":3,"progress":13,"chairid":2,"rm":[36,40],"card":{"type":0,"card":[-1,36,40,44],"chairid":1,"centercard":44,"flag":true},"lefttime":15,"opts":{"0":[],"1":[],"2":[]}},
{"op":2,"cardid":30,"progress":14,"chairid":2,"opts":{"0":[],"1":[],"2":[]}},
{"op":1,"leftcount":55,"frontremove":43,"cardid":31,"tailremove":0,"progress":15,"chairid":0,"lefttime":15,"opts":{"0":[],"1":[],"2":[]}},
{"op":2,"cardid":4,"progress":16,"chairid":0,"opts":{"0":[],"1":[{"op":5,"item":[{"id":0,"info":[0,4,10],"rm":[0,10],"type":0,"lmtid":[27,0,12,10,49,67,21,55,47]},{"id":1,"info":[4,10,12],"rm":[10,12],"type":0,"lmtid":[27,0,12,10,49,67,21,55,47]}]}],"2":[]}},
{"op":4,"select":{"1":5},"progress":16},
{"op":3,"progress":17,"chairid":1,"rm":[0,10],"card":{"type":0,"card":[-1,0,4,10],"chairid":0,"centercard":4,"flag":true},"lefttime":15,"opts":{"0":[],"1":[],"2":[]}},
{"op":2,"cardid":67,"progress":18,"chairid":1,"opts":{"0":[],"1":[],"2":[]}},
{"op":1,"leftcount":54,"frontremove":44,"cardid":90,"tailremove":0,"progress":19,"chairid":2,"lefttime":15,"opts":{"0":[],"1":[],"2":[]}},
{"op":2,"cardid":90,"progress":20,"chairid":2,"opts":{"0":[],"1":[],"2":[]}},
{"op":1,"leftcount":53,"frontremove":45,"cardid":69,"tailremove":0,"progress":21,"chairid":0,"lefttime":15,"opts":{"0":[],"1":[],"2":[]}},
{"op":2,"cardid":58,"progress":22,"chairid":0,"opts":{"0":[],"1":[{"op":5,"item":[{"id":0,"info":[49,55,58],"rm":[49,55],"type":0,"lmtid":[27,6,12,49,21,55]}]}],"2":[]}},
{"op":4,"select":{"1":5},"progress":22},
{"op":3,"progress":23,"chairid":1,"rm":[49,55],"card":{"type":0,"card":[-1,49,55,58],"chairid":0,"centercard":58,"flag":true},"lefttime":15,"opts":{"0":[],"1":[],"2":[]}},
{"op":2,"cardid":27,"progress":24,"chairid":1,"opts":{"0":[],"1":[],"2":[]}},
{"op":1,"leftcount":52,"frontremove":46,"cardid":37,"tailremove":0,"progress":25,"chairid":2,"lefttime":15,"opts":{"0":[],"1":[],"2":[]}},
{"op":2,"cardid":37,"progress":26,"chairid":2,"opts":{"0":[],"1":[],"2":[]}},
{"op":1,"leftcount":51,"frontremove":47,"cardid":86,"tailremove":0,"progress":27,"chairid":0,"lefttime":15,"opts":{"0":[],"1":[],"2":[]}},
{"op":2,"cardid":86,"progress":28,"chairid":0,"opts":{"0":[],"1":[],"2":[]}},
{"op":1,"leftcount":50,"frontremove":48,"cardid":41,"tailremove":0,"progress":29,"chairid":1,"lefttime":15,"opts":{"0":[],"1":[],"2":[]}},
{"op":2,"cardid":47,"progress":30,"chairid":1,"opts":{"0":[],"1":[],"2":[{"op":5,"item":[{"id":0,"info":[47,48,54],"rm":[48,54],"type":0,"lmtid":[102,100,48,5,54,105,63,62,107,61]}]}]}},
{"op":4,"select":{"2":5},"progress":30},
{"op":3,"progress":31,"chairid":2,"rm":[48,54],"card":{"type":0,"card":[-1,47,48,54],"chairid":1,"centercard":47,"flag":true},"lefttime":15,"opts":{"0":[],"1":[],"2":[{"op":4,"item":[{"id":0,"info":[5,100,2],"type":0},{"id":1,"info":[5,104,2],"type":0}]}]}},
{"op":4,"select":{"2":4},"progress":31},
{"op":2,"cardid":5,"ting":true,"progress":32,"chairid":2,"opts":{"0":[],"1":[],"2":[]}},
{"op":1,"leftcount":49,"frontremove":49,"cardid":98,"tailremove":0,"progress":33,"chairid":0,"lefttime":15,"opts":{"0":[],"1":[],"2":[]}},
{"op":2,"cardid":98,"progress":34,"chairid":0,"opts":{"0":[],"1":[],"2":[]}},
{"op":1,"leftcount":48,"frontremove":50,"cardid":92,"tailremove":0,"progress":35,"chairid":1,"lefttime":15,"opts":{"0":[],"1":[],"2":[]}},
{"op":2,"cardid":92,"progress":36,"chairid":1,"opts":{"0":[],"1":[],"2":[]}},
{"op":1,"leftcount":47,"frontremove":51,"cardid":50,"tailremove":0,"progress":37,"chairid":2,"lefttime":15,"opts":{"0":[],"1":[],"2":[]}},
{"op":2,"cardid":50,"progress":38,"chairid":2,"opts":{"0":[],"1":[],"2":[]}},
{"op":1,"leftcount":46,"frontremove":52,"cardid":64,"tailremove":0,"progress":39,"chairid":0,"lefttime":15,"opts":{"0":[],"1":[],"2":[]}},
{"op":2,"cardid":16,"progress":40,"chairid":0,"opts":{"0":[],"1":[],"2":[]}},
{"op":1,"leftcount":45,"frontremove":53,"cardid":85,"tailremove":0,"progress":41,"chairid":1,"lefttime":15,"opts":{"0":[],"1":[],"2":[]}},
{"op":2,"cardid":85,"progress":42,"chairid":1,"opts":{"0":[],"1":[],"2":[]}},
{"op":1,"leftcount":44,"frontremove":54,"cardid":68,"tailremove":0,"progress":43,"chairid":2,"lefttime":15,"opts":{"0":[],"1":[],"2":[]}},
{"op":2,"cardid":68,"progress":44,"chairid":2,"opts":{"0":[{"op":3,"item":[{"id":0,"info":[71,69,68],"rm":[71,69],"type":0}]}],"1":[],"2":[]}},
{"op":4,"select":{"0":3},"progress":44},
{"op":3,"progress":45,"chairid":0,"rm":[71,69],"card":{"type":1,"card":[-1,68,69,71],"chairid":2,"centercard":68,"flag":true},"lefttime":15,"opts":{"0":[{"op":4,"item":[{"id":0,"info":[28,20,4],"type":0},{"id":1,"info":[28,32,3],"type":0},{"id":2,"info":[24,28,1],"type":0},{"id":3,"info":[24,64,1],"type":0},{"id":4,"info":[31,20,4],"type":0},{"id":5,"info":[31,32,3],"type":0}]}],"1":[],"2":[]}},
{"op":4,"select":{"0":4},"progress":45},
{"op":2,"cardid":31,"ting":true,"progress":46,"chairid":0,"opts":{"0":[],"1":[],"2":[]}},
{"op":1,"leftcount":43,"frontremove":55,"cardid":38,"tailremove":0,"progress":47,"chairid":1,"lefttime":15,"opts":{"0":[],"1":[],"2":[]}},
{"op":2,"cardid":38,"progress":48,"chairid":1,"opts":{"0":[],"1":[],"2":[]}},
{"op":1,"leftcount":42,"frontremove":56,"cardid":15,"tailremove":0,"progress":49,"chairid":2,"lefttime":15,"opts":{"0":[],"1":[],"2":[]}},
{"op":2,"cardid":15,"progress":50,"chairid":2,"opts":{"0":[],"1":[],"2":[]}},
{"op":1,"leftcount":41,"frontremove":57,"cardid":13,"tailremove":0,"progress":51,"chairid":0,"lefttime":15,"opts":{"0":[],"1":[],"2":[]}},
{"op":2,"cardid":13,"progress":52,"chairid":0,"opts":{"0":[],"1":[],"2":[]}},
{"op":1,"leftcount":40,"frontremove":58,"cardid":70,"tailremove":0,"progress":53,"chairid":1,"lefttime":15,"opts":{"0":[],"1":[],"2":[]}},
{"op":2,"cardid":70,"progress":54,"chairid":1,"opts":{"0":[],"1":[],"2":[]}},
{"op":1,"leftcount":39,"frontremove":59,"cardid":51,"tailremove":0,"progress":55,"chairid":2,"lefttime":15,"opts":{"0":[],"1":[],"2":[]}},
{"op":2,"cardid":51,"progress":56,"chairid":2,"opts":{"0":[],"1":[],"2":[]}},
{"op":1,"leftcount":38,"frontremove":60,"cardid":103,"tailremove":0,"progress":57,"chairid":0,"lefttime":15,"opts":{"0":[],"1":[],"2":[]}},
{"op":2,"cardid":103,"progress":58,"chairid":0,"opts":{"0":[],"1":[],"2":[{"op":1,"item":[{"id":0,"type":0}]}]}},
{"op":4,"select":{"2":1},"progress":58},
{"result":{"detail":[{"score":-2,"des":"","totalscore":-2,"chairid":0,"card":[24,28,64,65,73,79,80,-8,81,84,91,-8,68,69,71,-1]},{"score":-2,"des":"","totalscore":-2,"chairid":1,"card":[6,12,21,41,-8,96,97,99,-8,0,4,10,-8,49,55,58,-1]},{"score":4,"des":"平胡","totalscore":4,"chairid":2,"card":[61,62,63,100,102,105,107,-8,36,40,44,-8,47,48,54,103]}],"winstate":[0,0,1]},"op":100,"progress":59,"wininfo":{"winner":[2],"lose":-1,"type":2}}]}
